dummy/__init__.py
elife_dummy_python_release_project-0.0.4.dist-info/LICENCE
elife_dummy_python_release_project-0.0.4.dist-info/METADATA
elife_dummy_python_release_project-0.0.4.dist-info/WHEEL
elife_dummy_python_release_project-0.0.4.dist-info/top_level.txt
elife_dummy_python_release_project-0.0.4.dist-info/RECORD
