Metadata-Version: 2.1
Name: elife-dummy-python-release-project
Version: 0.0.4
Summary: A small example package
Home-page: https://github.com/elifesciences/dummy-python-release-project
Author: Example Author
Author-email: author@example.com
Classifier: Programming Language :: Python :: 3
Classifier: License :: OSI Approved :: GNU General Public License v3 (GPLv3)
Classifier: Operating System :: OS Independent
Requires-Python: >=3.6
License-File: LICENCE
